rennips/__init__.py
rennips/rennips.py
rennips-0.2.0.dist-info/LICENSE
rennips-0.2.0.dist-info/METADATA
rennips-0.2.0.dist-info/WHEEL
rennips-0.2.0.dist-info/top_level.txt
rennips-0.2.0.dist-info/RECORD
