Metadata-Version: 2.1
Name: rennips
Version: 0.2.0
Summary: A minimalist Python progress spinner for iterative processes
Home-page: https://github.com/Oh-JongJin/rennips
Author: Oh Jongjin
Author-email: Oh Jongjin <5jx2oh@gmail.com>
License: MIT License
Project-URL: Homepage, https://github.com/Oh-JongJin/rennips
Keywords: progress,spinner,progress-bar,cli
Classifier: License :: OSI Approved :: MIT License
Classifier: Programming Language :: Python
Classifier: Programming Language :: Python :: 3
Requires-Python: >=3.7
License-File: LICENSE
